trackersremoverqbt/__init__.py
trackersremoverqbt/core.py
trackersremoverqbt/core_tk.py
trackersremoverqbt/mmqbt.py
trackersremoverqbt-0.4.1.dist-info/licenses/LICENSE
trackersremoverqbt-0.4.1.dist-info/METADATA
trackersremoverqbt-0.4.1.dist-info/WHEEL
trackersremoverqbt-0.4.1.dist-info/entry_points.txt
trackersremoverqbt-0.4.1.dist-info/top_level.txt
trackersremoverqbt-0.4.1.dist-info/RECORD
