Metadata-Version: 2.4
Name: trackersremoverqbt
Version: 0.4.1
Summary: Automatically removes trackers from active qBittorrent downloads.
Author-email: Julien Minniti <minnitijulien06@gmail.com>
License-Expression: MIT
Project-URL: Homepage, https://github.com/Jumitti/TrackersRemover-qBittorrent
Requires-Python: >=3.8
License-File: LICENSE
Requires-Dist: qbittorrent-api
Requires-Dist: rich
Dynamic: license-file
